[
  {
    "id": "G751",
    "ti": "Árchippos",
    "le": "Ἄρχιππος",
    "pl": "Arjippos",
    "ps": "ar'-khip-pos",
    "df": "de <span style='color: #0000FF; cursor: pointer' class='Slink' onClick=strongFun('G746')>G746</span> y <span style='color: #0000FF; cursor: pointer' class='Slink' onClick=strongFun('G2462')>G2462</span>; que gobierna caballos; Arquipo, un cristiano: <font color='%COLOR_BLUE%'>Arquipo.</font>"
  },
  {
    "id": "G752",
    "ti": "archisynágōgos",
    "le": "ἀρχισυνάγωγος",
    "pl": "arjisunágogos",
    "ps": "ar-khee-soon-ag'-o-gos",
    "df": "de <span style='color: #0000FF; cursor: pointer' class='Slink' onClick=strongFun('G746')>G746</span> y <span style='color: #0000FF; cursor: pointer' class='Slink' onClick=strongFun('G4864')>G4864</span>; director de los servicios en la sinagoga: <font color='%COLOR_BLUE%'>principal de la sinagoga.</font>"
  },
  {
    "id": "G753",
    "ti": "architéktōn",
    "le": "ἀρχιτέκτων",
    "pl": "arjitékton",
    "ps": "ar-khee-tek'-tone",
    "df": "de <span style='color: #0000FF; cursor: pointer' class='Slink' onClick=strongFun('G746')>G746</span> y <span style='color: #0000FF; cursor: pointer' class='Slink' onClick=strongFun('G5045')>G5045</span>; constructor principal, i.e. «arquitecto»: <font color='%COLOR_BLUE%'>arquitecto.</font>"
  },
  {
    "id": "G754",
    "ti": "architelṓnēs",
    "le": "ἀρχιτελώνης",
    "pl": "arjitelónes",
    "ps": "ar-khee-tel-o'-nace",
    "df": "de <span style='color: #0000FF; cursor: pointer' class='Slink' onClick=strongFun('G746')>G746</span> y <span style='color: #0000FF; cursor: pointer' class='Slink' onClick=strongFun('G5057')>G5057</span>; recaudador principal de impuestos: <font color='%COLOR_BLUE%'>jefe de los publicanos.</font>"
  },
  {
    "id": "G755",
    "ti": "architríklinos",
    "le": "ἀρχιτρίκλινος",
    "pl": "arjitriklínos",
    "ps": "ar-khee-tree'-klee-nos",
    "df": "de <span style='color: #0000FF; cursor: pointer' class='Slink' onClick=strongFun('G746')>G746</span> y un compuesto de <span style='color: #0000FF; cursor: pointer' class='Slink' onClick=strongFun('G5140')>G5140</span> y <span style='color: #0000FF; cursor: pointer' class='Slink' onClick=strongFun('G2827')>G2827</span> (reclinatorio para cena, porque está compuesto de tres divanes); director del entretenimiento: <font color='%COLOR_BLUE%'>maestresala.</font>"
  },
  {
    "id": "G756",
    "ti": "árchomai",
    "le": "ἄρχομαι",
    "pl": "árjomai",
    "ps": "ar'-khom-ahee",
    "df": "voz media de <span style='color: #0000FF; cursor: pointer' class='Slink' onClick=strongFun('G757')>G757</span> (con la implicación de precedencia); comenzar (en orden de tiempo): <font color='%COLOR_BLUE%'>empezar, comenzar.</font>"
  },
  {
    "id": "G757",
    "ti": "árchō",
    "le": "ἄρχω",
    "pl": "árjo",
    "ps": "ar'-kho",
    "df": "verbo primario, ser primero (en rango político o poder): <font color='%COLOR_BLUE%'>gobernante, regir.</font>"
  },
  {
    "id": "G758",
    "ti": "árchōn",
    "le": "ἄρχων",
    "pl": "árjon",
    "ps": "ar'-khone",
    "df": "participio presente de <span style='color: #0000FF; cursor: pointer' class='Slink' onClick=strongFun('G757')>G757</span>; primero (en rango o poder): <font color='%COLOR_BLUE%'>principal, príncipe, soberano, gobernante, hombre principal, magistrado, autoridad.</font>"
  },
  {
    "id": "G759",
    "ti": "árōma",
    "le": "ἄρωμα",
    "pl": "ároma",
    "ps": "ar'-o-mah",
    "df": "de <span style='color: #0000FF; cursor: pointer' class='Slink' onClick=strongFun('G142')>G142</span> (en el sentido de despedir esencia); aroma: <font color='%COLOR_BLUE%'>especia.</font>"
  },
  {
    "id": "G760",
    "ti": "Asá",
    "le": "Ἀσά",
    "pl": "Asá",
    "ps": "as-ah'",
    "df": "de origen hebreo [<span style='color: #0000FF; cursor: pointer' class='Slink' onClick=strongFun('H609')>H609</span>]; Asa, un israelita: <font color='%COLOR_BLUE%'>Asa.</font>"
  },
  {
    "id": "G761",
    "ti": "asáleutos",
    "le": "ἀσάλευτος",
    "pl": "asáleutos",
    "ps": "as-al'-yoo-tos",
    "df": "de <span style='color: #0000FF; cursor: pointer' class='Slink' onClick=strongFun('G1')>G1</span> (como partícula negativa) y un derivado de <span style='color: #0000FF; cursor: pointer' class='Slink' onClick=strongFun('G4531')>G4531</span>; sin estremecerse, i.e. (por implicación) inmovible (figurativamente): <font color='%COLOR_BLUE%'>inconmovible, inmóvil.</font>"
  },
  {
    "id": "G762",
    "ti": "ásbestos",
    "le": "ἄσβεστος",
    "pl": "ásbestos",
    "ps": "as'-bes-tos",
    "df": "de <span style='color: #0000FF; cursor: pointer' class='Slink' onClick=strongFun('G1')>G1</span> (como partícula negativa) y un derivado de <span style='color: #0000FF; cursor: pointer' class='Slink' onClick=strongFun('G4570')>G4570</span>; no extinguido, i.e. (por implicación) perpetuo: <font color='%COLOR_BLUE%'>no se puede apagar.</font>"
  },
  {
    "id": "G763",
    "ti": "asébeia",
    "le": "ἀσέβεια",
    "pl": "asébeia",
    "ps": "as-eb'-i-ah",
    "df": "de <span style='color: #0000FF; cursor: pointer' class='Slink' onClick=strongFun('G765')>G765</span>; impiedad, i.e. (por implicación) maldad, perversidad: <font color='%COLOR_BLUE%'>impiedad, impío, malvado.</font>"
  },
  {
    "id": "G764",
    "ti": "asebéō",
    "le": "ἀσεβέω",
    "pl": "asebéo",
    "ps": "as-eb-eh'-o",
    "df": "de <span style='color: #0000FF; cursor: pointer' class='Slink' onClick=strongFun('G765')>G765</span>; ser (por implicación actuar) impío o malvado: <font color='%COLOR_BLUE%'>hacer impíamente.</font>"
  },
  {
    "id": "G765",
    "ti": "asebḗs",
    "le": "ἀσεβής",
    "pl": "asebés",
    "ps": "as-eb-ace'",
    "df": "de <span style='color: #0000FF; cursor: pointer' class='Slink' onClick=strongFun('G1')>G1</span> (como partícula negativa) y un derivado presunto de <span style='color: #0000FF; cursor: pointer' class='Slink' onClick=strongFun('G4576')>G4576</span>; irreverente, i.e. (por extensión) impío o malvado: <font color='%COLOR_BLUE%'>impío.</font>"
  },
  {
    "id": "G766",
    "ti": "asélgeia",
    "le": "ἀσέλγεια",
    "pl": "asélgeia",
    "ps": "as-elg'-i-a",
    "df": "de un compuesto de <span style='color: #0000FF; cursor: pointer' class='Slink' onClick=strongFun('G1')>G1</span> (como partícula negativa) y un presunto <b>σελγής</b> <font color='%COLOR_PURPLE%'>selgés</font> (de derivación incierta, pero aparentemente significa continente); libertinaje sexual (a veces incluído otros vicios): <font color='%COLOR_BLUE%'>lascivia, libertinaje, disolución, nefanda,.</font>"
  },
  {
    "id": "G767",
    "ti": "ásēmos",
    "le": "ἄσημος",
    "pl": "ásemos",
    "ps": "as'-ay-mos",
    "df": "de <span style='color: #0000FF; cursor: pointer' class='Slink' onClick=strongFun('G1')>G1</span> (como partícula negativa) y la base de <span style='color: #0000FF; cursor: pointer' class='Slink' onClick=strongFun('G4591')>G4591</span>; sin marca, i.e. (figurativamente) innoble: <font color='%COLOR_BLUE%'>insignificante.</font>"
  },
  {
    "id": "G768",
    "ti": "Asḗr",
    "le": "Ἀσήρ",
    "pl": "Aser",
    "ps": "as-ayr'",
    "df": "de origen hebreo [<span style='color: #0000FF; cursor: pointer' class='Slink' onClick=strongFun('H836')>H836</span>]; Aser, una tribu israelitas: <font color='%COLOR_BLUE%'>Aser.</font>"
  },
  {
    "id": "G769",
    "ti": "asthéneia",
    "le": "ἀσθένεια",
    "pl": "asdséneia",
    "ps": "as-then'-i-ah",
    "df": "de <span style='color: #0000FF; cursor: pointer' class='Slink' onClick=strongFun('G772')>G772</span>; debilidad (de cuerpo o mente); por implicación enfermedad; moralmente fragilidad: <font color='%COLOR_BLUE%'>débil, debilidad, enfermedad, enfermo.</font>"
  },
  {
    "id": "G770",
    "ti": "asthenéō",
    "le": "ἀσθενέω",
    "pl": "asdsenéo",
    "ps": "as-then-eh'-o",
    "df": "de <span style='color: #0000FF; cursor: pointer' class='Slink' onClick=strongFun('G772')>G772</span>; estar débil (en cualquier sentido): <font color='%COLOR_BLUE%'>enfermar, enfermo, débil, debilitar, necesitado.</font>"
  },
  {
    "id": "G771",
    "ti": "asthénēma",
    "le": "ἀσθένημα",
    "pl": "asdsénema",
    "ps": "as-then'-ay-mah",
    "df": "de <span style='color: #0000FF; cursor: pointer' class='Slink' onClick=strongFun('G770')>G770</span>; escrúpulo de conciencia: <font color='%COLOR_BLUE%'>flaqueza.</font>"
  },
  {
    "id": "G772",
    "ti": "asthenḗs",
    "le": "ἀσθενής",
    "pl": "asdsenés",
    "ps": "as-then-ace'",
    "df": "de <span style='color: #0000FF; cursor: pointer' class='Slink' onClick=strongFun('G1')>G1</span> (como partícula negativa) y la base de <span style='color: #0000FF; cursor: pointer' class='Slink' onClick=strongFun('G4599')>G4599</span>; sin fuerza (en varias aplicaciones, literalmente, figurativamente y moralmente): <font color='%COLOR_BLUE%'>enfermo, frágil, débil, debilidad, debilitar.</font>"
  },
  {
    "id": "G773",
    "ti": "Asía",
    "le": "Ἀσία",
    "pl": "Asia",
    "ps": "as-ee'-ah",
    "df": "de derivación incierta; Asia, i.e. Asia Menor, o (por lo general) solo su costa occidental: <font color='%COLOR_BLUE%'>Asia.</font>"
  },
  {
    "id": "G774",
    "ti": "Asianós",
    "le": "Ἀσιανός",
    "pl": "Asianós",
    "ps": "as-ee-an-os'",
    "df": "de <span style='color: #0000FF; cursor: pointer' class='Slink' onClick=strongFun('G773')>G773</span>; asiático o habitante de Asia: <font color='%COLOR_BLUE%'>Asia.</font>"
  },
  {
    "id": "G775",
    "ti": "Asiárchēs",
    "le": "Ἀσιάρχης",
    "pl": "Asiárjes",
    "ps": "as-ee-ar'-khace",
    "df": "de <span style='color: #0000FF; cursor: pointer' class='Slink' onClick=strongFun('G773')>G773</span> y <span style='color: #0000FF; cursor: pointer' class='Slink' onClick=strongFun('G746')>G746</span>; asiarca o presidente de las festividades públicas en una ciudad de Asia Menor: <font color='%COLOR_BLUE%'>Autoridad de Asia.</font>"
  },
  {
    "id": "G776",
    "ti": "asitía",
    "le": "ἀσιτία",
    "pl": "asitía",
    "ps": "as-ee-tee'-ah",
    "df": "de <span style='color: #0000FF; cursor: pointer' class='Slink' onClick=strongFun('G1')>G1</span>; ayuno (el estado): <font color='%COLOR_BLUE%'>no comer.</font>"
  },
  {
    "id": "G777",
    "ti": "ásitos",
    "le": "ἄσιτος",
    "pl": "ásitos",
    "ps": "as'-ee-tos",
    "df": "de <span style='color: #0000FF; cursor: pointer' class='Slink' onClick=strongFun('G1')>G1</span> (como partícula negativa) y <span style='color: #0000FF; cursor: pointer' class='Slink' onClick=strongFun('G4621')>G4621</span>; sin (tomar) alimento: <font color='%COLOR_BLUE%'>ayuno.</font>"
  },
  {
    "id": "G778",
    "ti": "askéō",
    "le": "ἀσκέω",
    "pl": "askéo",
    "ps": "as-keh'-o",
    "df": "probablemente de lo mismo que <span style='color: #0000FF; cursor: pointer' class='Slink' onClick=strongFun('G4632')>G4632</span>; elaborar, i.e. (figurativamente) entrenar (por implicación esforzarse): <font color='%COLOR_BLUE%'>procurar.</font>"
  },
  {
    "id": "G779",
    "ti": "askós",
    "le": "ἀσκός",
    "pl": "askós",
    "ps": "as-kos'",
    "df": "de lo mismo que <span style='color: #0000FF; cursor: pointer' class='Slink' onClick=strongFun('G778')>G778</span>; bolsa de cuero (o piel) usada como botella: <font color='%COLOR_BLUE%'>odre.</font>"
  },
  {
    "id": "G780",
    "ti": "asménōs",
    "le": "ἀσμένως",
    "pl": "asménos",
    "ps": "as-men'-oce",
    "df": "adverbio de un derivado de la base de <span style='color: #0000FF; cursor: pointer' class='Slink' onClick=strongFun('G2237')>G2237</span>; con placer: <font color='%COLOR_BLUE%'>con gozo.</font>"
  },
  {
    "id": "G781",
    "ti": "ásophos",
    "le": "ἄσοφος",
    "pl": "ásofos",
    "ps": "as'-of-os",
    "df": "de <span style='color: #0000FF; cursor: pointer' class='Slink' onClick=strongFun('G1')>G1</span> (como partícula negativa) y <span style='color: #0000FF; cursor: pointer' class='Slink' onClick=strongFun('G4680')>G4680</span>; no sabio: <font color='%COLOR_BLUE%'>necio.</font>"
  },
  {
    "id": "G782",
    "ti": "aspázomai",
    "le": "ἀσπάζομαι",
    "pl": "aspázomai",
    "ps": "as-pad'-zom-ahee",
    "df": "de <span style='color: #0000FF; cursor: pointer' class='Slink' onClick=strongFun('G1')>G1</span> (como partícula de unión) y cierta forma de <span style='color: #0000FF; cursor: pointer' class='Slink' onClick=strongFun('G4685')>G4685</span>; encerrar en los brazos, i.e. (por implicación) saludar, (figurativamente) dar la bienvenida: <font color='%COLOR_BLUE%'>saludar, abrazar.</font>"
  },
  {
    "id": "G783",
    "ti": "aspasmós",
    "le": "ἀσπασμός",
    "pl": "aspasmós",
    "ps": "as-pas-mos'",
    "df": "de <span style='color: #0000FF; cursor: pointer' class='Slink' onClick=strongFun('G782')>G782</span>; saludo (en persona o por carta): <font color='%COLOR_BLUE%'>salutación.</font>"
  },
  {
    "id": "G784",
    "ti": "áspilos",
    "le": "ἄσπιλος",
    "pl": "áspilos",
    "ps": "as'-pee-los",
    "df": "de <span style='color: #0000FF; cursor: pointer' class='Slink' onClick=strongFun('G1')>G1</span> (como partícula negativa) y <span style='color: #0000FF; cursor: pointer' class='Slink' onClick=strongFun('G4695')>G4695</span>; sin defecto (físicamente o moralmente): <font color='%COLOR_BLUE%'>sin contaminación, sin mácula, sin mancha.</font>"
  },
  {
    "id": "G785",
    "ti": "aspís",
    "le": "ἀσπίς",
    "pl": "aspís",
    "ps": "as-pece'",
    "df": "de derivación incierta; escudo (o escudo redondo); usado de una serpiente (como que se enrosca), probablemente «áspid»: <font color='%COLOR_BLUE%'>áspid.</font>"
  },
  {
    "id": "G786",
    "ti": "áspondos",
    "le": "ἄσπονδος",
    "pl": "áspondos",
    "ps": "as'-pon-dos",
    "df": "de <span style='color: #0000FF; cursor: pointer' class='Slink' onClick=strongFun('G1')>G1</span> (como partícula negativa) y un derivado de <span style='color: #0000FF; cursor: pointer' class='Slink' onClick=strongFun('G4689')>G4689</span>; literalmente sin libación (que por lo general acompañaba un tratado), i.e. (por implicación) sin tregua: <font color='%COLOR_BLUE%'>implacable.</font>"
  },
  {
    "id": "G787",
    "ti": "assárion",
    "le": "ἀσσάριον",
    "pl": "assárion",
    "ps": "as-sar'-ee-on",
    "df": "de origen latín; asarius o as, moneda romano: <font color='%COLOR_BLUE%'>cuarto.</font>"
  },
  {
    "id": "G788",
    "ti": "âsson",
    "le": "ἆσσον",
    "pl": "ásson",
    "ps": "as'-son",
    "df": "neutro comparativo de la base de <span style='color: #0000FF; cursor: pointer' class='Slink' onClick=strongFun('G1451')>G1451</span>; más cercanamente, i.e. muy cerca: <font color='%COLOR_BLUE%'>costear, seguir la costa.</font>"
  },
  {
    "id": "G789",
    "ti": "Ássos",
    "le": "Ἄσσος",
    "pl": "Assos",
    "ps": "as'-sos",
    "df": "probablemente de origen extranjero; Asón, una ciudad de Asia Menor: <font color='%COLOR_BLUE%'>Asón.</font>"
  },
  {
    "id": "G790",
    "ti": "astatéō",
    "le": "ἀστατέω",
    "pl": "astatéo",
    "ps": "as-tat-eh'-o",
    "df": "de <span style='color: #0000FF; cursor: pointer' class='Slink' onClick=strongFun('G1')>G1</span> (como partícula negativa) y un derivado de <span style='color: #0000FF; cursor: pointer' class='Slink' onClick=strongFun('G2476')>G2476</span>; estar no estacionario, i.e. (figurativamente) indigente: <font color='%COLOR_BLUE%'>sin morada fija.</font>"
  },
  {
    "id": "G791",
    "ti": "asteîos",
    "le": "ἀστεῖος",
    "pl": "asteíos",
    "ps": "as-ti'-os",
    "df": "de <b>ἄστυ</b> <font color='%COLOR_PURPLE%'>ástu</font> (ciudad); urbano, i.e. (por implicación) bonito, atractivo: <font color='%COLOR_BLUE%'>agradable.</font>"
  },
  {
    "id": "G792",
    "ti": "astḗr",
    "le": "ἀστήρ",
    "pl": "astér",
    "ps": "as-tare'",
    "df": "probablemente de la base de <span style='color: #0000FF; cursor: pointer' class='Slink' onClick=strongFun('G4766')>G4766</span>; estrella (como regada por el cielo), literalmente o figurativamente: <font color='%COLOR_BLUE%'>estrella.</font>"
  },
  {
    "id": "G793",
    "ti": "astḗriktos",
    "le": "ἀστήρικτος",
    "pl": "astériktos",
    "ps": "as-tay'-rik-tos",
    "df": "de <span style='color: #0000FF; cursor: pointer' class='Slink' onClick=strongFun('G1')>G1</span> (como partícula negativa) y un derivado quizás de <span style='color: #0000FF; cursor: pointer' class='Slink' onClick=strongFun('G4741')>G4741</span>; no fijo, i.e. (figurativamente) vacilante: <font color='%COLOR_BLUE%'>incostante.</font>"
  },
  {
    "id": "G794",
    "ti": "ástorgos",
    "le": "ἄστοργος",
    "pl": "ástorgos",
    "ps": "as'-tor-gos",
    "df": "de <span style='color: #0000FF; cursor: pointer' class='Slink' onClick=strongFun('G1')>G1</span> (como partícula negativa) y un derivado de <b>στέργω</b> <font color='%COLOR_PURPLE%'>stérgo</font> (acariciar con afecto); de corazón duro hacia los parientes: <font color='%COLOR_BLUE%'>sin afecto natural.</font>"
  },
  {
    "id": "G795",
    "ti": "astochéō",
    "le": "ἀστοχέω",
    "pl": "astojéo",
    "ps": "as-tokh-eh'-o",
    "df": "de un compuesto de <span style='color: #0000FF; cursor: pointer' class='Slink' onClick=strongFun('G1')>G1</span> (como partícula negativa) y <b>στόιχος</b> <font color='%COLOR_PURPLE%'>stóijos</font> (blanco, meta); errar el blanco, i.e. (figurativamente) desviarse de la verdad: <font color='%COLOR_BLUE%'>desviar, falsamente.</font>"
  },
  {
    "id": "G796",
    "ti": "astrapḗ",
    "le": "ἀστραπή",
    "pl": "astrapé",
    "ps": "as-trap-ay'",
    "df": "de <span style='color: #0000FF; cursor: pointer' class='Slink' onClick=strongFun('G797')>G797</span>; relámpago, rayo; por analogía resplandor, brillo: <font color='%COLOR_BLUE%'>rayo, relámpago.</font>"
  },
  {
    "id": "G797",
    "ti": "astráptō",
    "le": "ἀστράπτω",
    "pl": "astrápto",
    "ps": "as-trap'-to",
    "df": "probablemente de <span style='color: #0000FF; cursor: pointer' class='Slink' onClick=strongFun('G792')>G792</span>; relampaguear como rayo: <font color='%COLOR_BLUE%'>resplandecer, resplandeciente, fulgurar.</font>"
  },
  {
    "id": "G798",
    "ti": "ástron",
    "le": "ἄστρον",
    "pl": "ástron",
    "ps": "as'-tron",
    "df": "neutro de <span style='color: #0000FF; cursor: pointer' class='Slink' onClick=strongFun('G792')>G792</span>; propiamente constelación; puesta por una sola estrella (natural o artificialmente): <font color='%COLOR_BLUE%'>estrella.</font>"
  },
  {
    "id": "G799",
    "ti": "Asýnkritos",
    "le": "Ἀσύγκριτος",
    "pl": "Asúnkritos",
    "ps": "as-oong'-kree-tos",
    "df": "de <span style='color: #0000FF; cursor: pointer' class='Slink' onClick=strongFun('G1')>G1</span> (como partícula negativa) y un derivado de <span style='color: #0000FF; cursor: pointer' class='Slink' onClick=strongFun('G4793')>G4793</span>; incomparable; Asíncrito, un cristiano: <font color='%COLOR_BLUE%'>Asíncrito.</font>"
  },
  {
    "id": "G800",
    "ti": "asýmphōnos",
    "le": "ἀσύμφωνος",
    "pl": "asúmfonos",
    "ps": "as-oom'-fo-nos",
    "df": "de <span style='color: #0000FF; cursor: pointer' class='Slink' onClick=strongFun('G1')>G1</span> (como partícula negativa) y <span style='color: #0000FF; cursor: pointer' class='Slink' onClick=strongFun('G4859')>G4859</span>; no armonioso (figurativamente): <font color='%COLOR_BLUE%'>no estar de acuerdo.</font>"
  },
  {
    "id": "G801",
    "ti": "asýnetos",
    "le": "ἀσύνετος",
    "pl": "asúnetos",
    "ps": "as-oon'-ay-tos",
    "df": "de <span style='color: #0000FF; cursor: pointer' class='Slink' onClick=strongFun('G1')>G1</span> (como partícula negativa) y <span style='color: #0000FF; cursor: pointer' class='Slink' onClick=strongFun('G4908')>G4908</span>; no inteligente; por implicación perverso, malo: <font color='%COLOR_BLUE%'>no entender, sin entendimiento, insensato, necio.</font>"
  },
  {
    "id": "G802",
    "ti": "asýnthetos",
    "le": "ἀσύνθετος",
    "pl": "asúndsetos",
    "ps": "as-oon'-thet-os",
    "df": "de <span style='color: #0000FF; cursor: pointer' class='Slink' onClick=strongFun('G1')>G1</span> (como partícula negativa) y un derivado de <span style='color: #0000FF; cursor: pointer' class='Slink' onClick=strongFun('G4934')>G4934</span>; propiamente no acordado, i.e. traidor a pactos: <font color='%COLOR_BLUE%'>desleal.</font>"
  },
  {
    "id": "G803",
    "ti": "aspháleia",
    "le": "ἀσφάλεια",
    "pl": "asfáleia",
    "ps": "as-fal'-i-ah",
    "df": "de <span style='color: #0000FF; cursor: pointer' class='Slink' onClick=strongFun('G804')>G804</span>; seguridad (literalmente o figurativamente): <font color='%COLOR_BLUE%'>seguridad, conocer bien la verdad.</font>"
  },
  {
    "id": "G804",
    "ti": "asphalḗs",
    "le": "ἀσφαλής",
    "pl": "asfalés",
    "ps": "as-fal-ace'",
    "df": "de <span style='color: #0000FF; cursor: pointer' class='Slink' onClick=strongFun('G1')>G1</span> (como partícula negativa) y <b>σφάλλω</b> <font color='%COLOR_PURPLE%'>sfálo</font> («fallar»); seguro (literalmente o figurativamente): <font color='%COLOR_BLUE%'>seguro, cierto, causa.</font>"
  },
  {
    "id": "G805",
    "ti": "asphalízō",
    "le": "ἀσφαλίζω",
    "pl": "asfalízo",
    "ps": "as-fal-id'-zo",
    "df": "de <span style='color: #0000FF; cursor: pointer' class='Slink' onClick=strongFun('G804')>G804</span>; hacer seguro: <font color='%COLOR_BLUE%'>asegurar.</font>"
  },
  {
    "id": "G806",
    "ti": "asphalōs",
    "le": "ἀσφαλῶς",
    "pl": "asfalós",
    "ps": "as-fal-oce'",
    "df": "adverbio de <span style='color: #0000FF; cursor: pointer' class='Slink' onClick=strongFun('G804')>G804</span>; seguramente (literalmente o figurativamente): <font color='%COLOR_BLUE%'>ciertísimamente, con seguridad.</font>"
  },
  {
    "id": "G807",
    "ti": "aschēmonéō",
    "le": "ἀσχημονέω",
    "pl": "asjemonéo",
    "ps": "as-kay-mon-eh'-o",
    "df": "de <span style='color: #0000FF; cursor: pointer' class='Slink' onClick=strongFun('G809')>G809</span>; ser (i.e. actuar) indebidamente: <font color='%COLOR_BLUE%'>impropio, indebido.</font>"
  },
  {
    "id": "G808",
    "ti": "aschēmosýnē",
    "le": "ἀσχημοσύνη",
    "pl": "asjemosúne",
    "ps": "as-kay-mos-oo'-nay",
    "df": "de <span style='color: #0000FF; cursor: pointer' class='Slink' onClick=strongFun('G809')>G809</span>; indecencia; por implicación las partes pudendas: <font color='%COLOR_BLUE%'>vergonzoso, vergüenza.</font>"
  },
  {
    "id": "G809",
    "ti": "aschḗmōn",
    "le": "ἀσχήμων",
    "pl": "asjémon",
    "ps": "as-kay'-mone",
    "df": "de <span style='color: #0000FF; cursor: pointer' class='Slink' onClick=strongFun('G1')>G1</span> (como partícula negativa) y un derivado presunto de <span style='color: #0000FF; cursor: pointer' class='Slink' onClick=strongFun('G2192')>G2192</span> (en el sentido de su congénere <span style='color: #0000FF; cursor: pointer' class='Slink' onClick=strongFun('G4976')>G4976</span>); propiamente sin forma, i.e. (figurativamente) inelegante: <font color='%COLOR_BLUE%'>menos decoroso.</font>"
  },
  {
    "id": "G810",
    "ti": "asōtía",
    "le": "ἀσωτία",
    "pl": "asotía",
    "ps": "as-o-tee'-ah",
    "df": "de un compuesto de <span style='color: #0000FF; cursor: pointer' class='Slink' onClick=strongFun('G1')>G1</span> (como partícula negativa) y un derivado presunto de <span style='color: #0000FF; cursor: pointer' class='Slink' onClick=strongFun('G4982')>G4982</span>; propiamente disolución, i.e. (por implicación) libertinaje: <font color='%COLOR_BLUE%'>disolución.</font>"
  },
  {
    "id": "G811",
    "ti": "asṓtōs",
    "le": "ἀσώτως",
    "pl": "asótos",
    "ps": "as-o'-toce",
    "df": "adverbio de lo mismo que <span style='color: #0000FF; cursor: pointer' class='Slink' onClick=strongFun('G810')>G810</span>; con disolución, libertinamente: <font color='%COLOR_BLUE%'>perdidamente.</font>"
  },
  {
    "id": "G812",
    "ti": "ataktéō",
    "le": "ἀτακτέω",
    "pl": "ataktéo",
    "ps": "at-ak-teh'-o",
    "df": "de <span style='color: #0000FF; cursor: pointer' class='Slink' onClick=strongFun('G813')>G813</span>; ser (i.e. actuar) irregular: <font color='%COLOR_BLUE%'>andar desordenadamente.</font>"
  },
  {
    "id": "G813",
    "ti": "átaktos",
    "le": "ἄτακτος",
    "pl": "átaktos",
    "ps": "at'-ak-tos",
    "df": "de <span style='color: #0000FF; cursor: pointer' class='Slink' onClick=strongFun('G1')>G1</span> (como partícula negativa) y un derivado de <span style='color: #0000FF; cursor: pointer' class='Slink' onClick=strongFun('G5021')>G5021</span>; no arreglado, i.e. (por implicación) insubordinado (religiosamente): <font color='%COLOR_BLUE%'>ocioso.</font>"
  },
  {
    "id": "G814",
    "ti": "atáktōs",
    "le": "ἀτάκτως",
    "pl": "atáktos",
    "ps": "at-ak'-toce",
    "df": "adverbio de <span style='color: #0000FF; cursor: pointer' class='Slink' onClick=strongFun('G813')>G813</span>; irregularmente (moralmente): <font color='%COLOR_BLUE%'>desordenadamente.</font>"
  },
  {
    "id": "G815",
    "ti": "áteknos",
    "le": "ἄτεκνος",
    "pl": "áteknos",
    "ps": "at'-ek-nos",
    "df": "de <span style='color: #0000FF; cursor: pointer' class='Slink' onClick=strongFun('G1')>G1</span> (como partícula negativa) y <span style='color: #0000FF; cursor: pointer' class='Slink' onClick=strongFun('G5043')>G5043</span>; sin hijo: <font color='%COLOR_BLUE%'>no dejar hijo, sin hijo.</font>"
  },
  {
    "id": "G816",
    "ti": "atenízō",
    "le": "ἀτενίζω",
    "pl": "atenízo",
    "ps": "at-en-id'-zo",
    "df": "de un compuesto de <span style='color: #0000FF; cursor: pointer' class='Slink' onClick=strongFun('G1')>G1</span> (como partícula de unión) y <b>τείνω</b> <font color='%COLOR_PURPLE%'>teíno</font> (estirar); fijar la mirada intensamente: <font color='%COLOR_BLUE%'>fijar los ojos, fijo, mirar fijamente, fijar la vista.</font>"
  },
  {
    "id": "G817",
    "ti": "áter",
    "le": "ἄτερ",
    "pl": "áter",
    "ps": "at'-er",
    "df": "partícula probablemente afín a <span style='color: #0000FF; cursor: pointer' class='Slink' onClick=strongFun('G427')>G427</span>; reservado, frío, i.e. aparte de (literalmente o figurativamente): <font color='%COLOR_BLUE%'>a espaldas.</font>"
  },
  {
    "id": "G818",
    "ti": "atimázō",
    "le": "ἀτιμάζω",
    "pl": "atimázo",
    "ps": "at-im-ad'-zo",
    "df": "de <span style='color: #0000FF; cursor: pointer' class='Slink' onClick=strongFun('G820')>G820</span>; hacer infame, i.e. (por implicación) desdén o maltrato: <font color='%COLOR_BLUE%'>afrentar, deshonrar, padecer afrenta.</font>"
  },
  {
    "id": "G819",
    "ti": "atimía",
    "le": "ἀτιμία",
    "pl": "atimía",
    "ps": "at-ee-mee'-ah",
    "df": "de <span style='color: #0000FF; cursor: pointer' class='Slink' onClick=strongFun('G820')>G820</span>; infamia, i.e. (subj.) indignidad comparativa, (objectivamente) desgracia: <font color='%COLOR_BLUE%'>vergüenza, vil, deshonra.</font>"
  },
  {
    "id": "G820",
    "ti": "átimos",
    "le": "ἄτιμος",
    "pl": "átimos",
    "ps": "at'-ee-mos",
    "df": "de <span style='color: #0000FF; cursor: pointer' class='Slink' onClick=strongFun('G1')>G1</span> (como partícula negativa) y <span style='color: #0000FF; cursor: pointer' class='Slink' onClick=strongFun('G5092')>G5092</span>; (negativa) no honrado o (positivamente) deshonrado: <font color='%COLOR_BLUE%'>sin honra, menos decoroso, despreciar, menos digno.</font>"
  },
  {
    "id": "G821",
    "ti": "atimóō",
    "le": "ἀτιμόω",
    "pl": "atimóo",
    "ps": "at-ee-mo'-o",
    "df": "de <span style='color: #0000FF; cursor: pointer' class='Slink' onClick=strongFun('G820')>G820</span>; usado como <span style='color: #0000FF; cursor: pointer' class='Slink' onClick=strongFun('G818')>G818</span>, maltratar: <font color='%COLOR_BLUE%'>afrentar.</font>"
  },
  {
    "id": "G822",
    "ti": "atmís",
    "le": "ἀτμίς",
    "pl": "atmís",
    "ps": "at-mece'",
    "df": "de lo mismo que <span style='color: #0000FF; cursor: pointer' class='Slink' onClick=strongFun('G109')>G109</span>; neblina, vapor: <font color='%COLOR_BLUE%'>neblina, vapor.</font>"
  },
  {
    "id": "G823",
    "ti": "átomos",
    "le": "ἄτομος",
    "pl": "átomos",
    "ps": "at'-om-os",
    "df": "de <span style='color: #0000FF; cursor: pointer' class='Slink' onClick=strongFun('G1')>G1</span> (como partícula negativa) y la base de <span style='color: #0000FF; cursor: pointer' class='Slink' onClick=strongFun('G5114')>G5114</span>; no cortado, i.e. (por implicación) indivisible [un «átomo» de tiempo]: <font color='%COLOR_BLUE%'>momento.</font>"
  },
  {
    "id": "G824",
    "ti": "átopos",
    "le": "ἄτοπος",
    "pl": "átopos",
    "ps": "at'-op-os",
    "df": "de <span style='color: #0000FF; cursor: pointer' class='Slink' onClick=strongFun('G1')>G1</span> (como partícula negativa) y <span style='color: #0000FF; cursor: pointer' class='Slink' onClick=strongFun('G5117')>G5117</span>; fuera de lugar, i.e. (figurativamente) impropio, injurioso, malvado: <font color='%COLOR_BLUE%'>mal, crimen, perverso.</font>"
  },
  {
    "id": "G825",
    "ti": "Attáleia",
    "le": "Ἀττάλεια",
    "pl": "Attáleia",
    "ps": "at-tal'-i-ah",
    "df": "de <b>Ἄτταλος</b> <font color='%COLOR_PURPLE%'>áttalos</font> (rey de Pérgamo); Atalía, un lugar en Panfilia: <font color='%COLOR_BLUE%'>Atalia.</font>"
  },
  {
    "id": "G826",
    "ti": "augázō",
    "le": "αὐγάζω",
    "pl": "augázo",
    "ps": "ow-gad'-zo",
    "df": "de <span style='color: #0000FF; cursor: pointer' class='Slink' onClick=strongFun('G827')>G827</span>; relucir, brillar (figurativamente): <font color='%COLOR_BLUE%'>resplandecer.</font>"
  },
  {
    "id": "G827",
    "ti": "augḗ",
    "le": "αὐγή",
    "pl": "augé",
    "ps": "owg'-ay",
    "df": "de derivación incierta; rayo de luz, i.e. (por implicación) brillo, aurora: <font color='%COLOR_BLUE%'>alba.</font>"
  },
  {
    "id": "G828",
    "ti": "Augoûstos",
    "le": "Αὐγοῦστος",
    "pl": "Aúgustos",
    "ps": "ow'-goos-tos",
    "df": "de latín [«augusto»]; Augusto, título del emperador romano: <font color='%COLOR_BLUE%'>Augusto.</font>"
  },
  {
    "id": "G829",
    "ti": "authádēs",
    "le": "αὐθάδης",
    "pl": "audsádes",
    "ps": "ow-thad'-ace",
    "df": "de <span style='color: #0000FF; cursor: pointer' class='Slink' onClick=strongFun('G846')>G846</span> y la base de <span style='color: #0000FF; cursor: pointer' class='Slink' onClick=strongFun('G2237')>G2237</span>; que se agrada a sí mismo, i.e. arrogante: <font color='%COLOR_BLUE%'>contumaz, soberbio.</font>"
  },
  {
    "id": "G830",
    "ti": "authaíretos",
    "le": "αὐθαίρετος",
    "pl": "audsaíretos",
    "ps": "ow-thah'-ee-ret-os",
    "df": "de <span style='color: #0000FF; cursor: pointer' class='Slink' onClick=strongFun('G846')>G846</span> y lo mismo que <span style='color: #0000FF; cursor: pointer' class='Slink' onClick=strongFun('G140')>G140</span>; escogido por sí mismo, i.e. (por implicación) voluntario: <font color='%COLOR_BLUE%'>por su propia voluntad.</font>"
  },
  {
    "id": "G831",
    "ti": "authentéō",
    "le": "αὐθεντέω",
    "pl": "audsentéo",
    "ps": "ow-then-teh'-o",
    "df": "<b>ἕντης</b> <font color='%COLOR_PURPLE%'>jéntes</font> (trabajador, obrero) actuar por uno mismo, i.e. (figurativamente) dominar: <font color='%COLOR_BLUE%'>dominio.</font>"
  },
  {
    "id": "G832",
    "ti": "auléō",
    "le": "αὐλέω",
    "pl": "auléo",
    "ps": "ow-leh'-o",
    "df": "de <span style='color: #0000FF; cursor: pointer' class='Slink' onClick=strongFun('G836')>G836</span>; tocar la flauta: <font color='%COLOR_BLUE%'>tocar flauta.</font>"
  },
  {
    "id": "G833",
    "ti": "aulḗ",
    "le": "αὐλή",
    "pl": "aulé",
    "ps": "ow-lay'",
    "df": "de lo mismo que <span style='color: #0000FF; cursor: pointer' class='Slink' onClick=strongFun('G109')>G109</span>; patio (como abierto al viento); por implicación mansión: <font color='%COLOR_BLUE%'>redil de ovejas, palacio, patio, atrio.</font>"
  },
  {
    "id": "G834",
    "ti": "aulētḗs",
    "le": "αὐλητής",
    "pl": "auletés",
    "ps": "ow-lay-tace'",
    "df": "de <span style='color: #0000FF; cursor: pointer' class='Slink' onClick=strongFun('G832')>G832</span>; que toca la flauta: <font color='%COLOR_BLUE%'>flauta, flautista.</font>"
  },
  {
    "id": "G835",
    "ti": "aulízomai",
    "le": "αὐλίζομαι",
    "pl": "aulízomai",
    "ps": "ow-lid'-zom-ahee",
    "df": "voz media de <span style='color: #0000FF; cursor: pointer' class='Slink' onClick=strongFun('G833')>G833</span>; pasar la noche (propiamente al aire libre): <font color='%COLOR_BLUE%'>posar.</font>"
  },
  {
    "id": "G836",
    "ti": "aulós",
    "le": "αὐλός",
    "pl": "aulós",
    "ps": "ow-los'",
    "df": "de lo mismo que <span style='color: #0000FF; cursor: pointer' class='Slink' onClick=strongFun('G109')>G109</span>; flauta (como que se sopla): <font color='%COLOR_BLUE%'>flauta.</font>"
  },
  {
    "id": "G837",
    "ti": "auxánō",
    "le": "αὐξάνω",
    "pl": "auxáno",
    "ps": "owx-an'-o",
    "df": "forma prolongada de un verbo primario, crecer i.e. agrandar (literalmente o figurativamente, activamente o pasivamente): <font color='%COLOR_BLUE%'>aumentar, crecer, dar crecimiento.</font>"
  },
  {
    "id": "G838",
    "ti": "aúxēsis",
    "le": "αὔξησις",
    "pl": "aúxesis",
    "ps": "owx'-ay-sis",
    "df": "de <span style='color: #0000FF; cursor: pointer' class='Slink' onClick=strongFun('G837')>G837</span>; crecimiento: <font color='%COLOR_BLUE%'>crecimiento.</font>"
  },
  {
    "id": "G839",
    "ti": "aúrion",
    "le": "αὔριον",
    "pl": "aúrion",
    "ps": "ow'-ree-on",
    "df": "de un derivado de lo mismo que <span style='color: #0000FF; cursor: pointer' class='Slink' onClick=strongFun('G109')>G109</span> (significa brisa, i.e. el aire de la mañana); propiamente fresco, i.e. (adverbio con elipsis de <span style='color: #0000FF; cursor: pointer' class='Slink' onClick=strongFun('G2250')>G2250</span>) mañana: <font color='%COLOR_BLUE%'>día siguiente, día de mañana.</font>"
  },
  {
    "id": "G840",
    "ti": "austērós",
    "le": "αὐστηρός",
    "pl": "austerós",
    "ps": "ow-stay-ros'",
    "df": "de un derivado (presunto) de lo mismo que <span style='color: #0000FF; cursor: pointer' class='Slink' onClick=strongFun('G109')>G109</span> (significa soplado); áspero (propiamente como ventarrón), i.e. (figurativamente) severo: <font color='%COLOR_BLUE%'>severo, suficiente.</font>"
  },
  {
    "id": "G841",
    "ti": "autárkeia",
    "le": "αὐτάρκεια",
    "pl": "autárkeia",
    "ps": "ow-tar'-ki-ah",
    "df": "de <span style='color: #0000FF; cursor: pointer' class='Slink' onClick=strongFun('G842')>G842</span>; autosatisfacción, i.e. (abstractamente) contentamiento, o (concretamente) competencia: <font color='%COLOR_BLUE%'>contentamiento.</font>"
  },
  {
    "id": "G842",
    "ti": "autárkēs",
    "le": "αὐτάρκης",
    "pl": "autárkes",
    "ps": "ow-tar'-kace",
    "df": "de <span style='color: #0000FF; cursor: pointer' class='Slink' onClick=strongFun('G846')>G846</span> y <span style='color: #0000FF; cursor: pointer' class='Slink' onClick=strongFun('G714')>G714</span>; autocomplaciente, i.e. contento: <font color='%COLOR_BLUE%'>contentar.</font>"
  },
  {
    "id": "G843",
    "ti": "autokatákritos",
    "le": "αὐτοκατάκριτος",
    "pl": "autokatákritos",
    "ps": "ow-tok-at-ak'-ree-tos",
    "df": "de <span style='color: #0000FF; cursor: pointer' class='Slink' onClick=strongFun('G846')>G846</span> y a derivado o <span style='color: #0000FF; cursor: pointer' class='Slink' onClick=strongFun('G2632')>G2632</span>; autocondenado: <font color='%COLOR_BLUE%'>condenado por su propio juicio.</font>"
  },
  {
    "id": "G844",
    "ti": "autómatos",
    "le": "αὐτόματος",
    "pl": "autómatos",
    "ps": "ow-tom'-at-os",
    "df": "de <span style='color: #0000FF; cursor: pointer' class='Slink' onClick=strongFun('G846')>G846</span> y lo mismo que <span style='color: #0000FF; cursor: pointer' class='Slink' onClick=strongFun('G3155')>G3155</span>; que se mueve a sí mismo [«automático»], i.e. espontáneo: <font color='%COLOR_BLUE%'>de suyo, volver (por voluntad propia).</font>"
  },
  {
    "id": "G845",
    "ti": "autóptēs",
    "le": "αὐτόπτης",
    "pl": "autóptes",
    "ps": "ow-top'-tace",
    "df": "de <span style='color: #0000FF; cursor: pointer' class='Slink' onClick=strongFun('G846')>G846</span> y <span style='color: #0000FF; cursor: pointer' class='Slink' onClick=strongFun('G3700')>G3700</span>; que ve por sí mismo, i.e. testigo ocular: <font color='%COLOR_BLUE%'>ver con sus ojos.</font>"
  },
  {
    "id": "G846",
    "ti": "autós",
    "le": "αὐτός",
    "pl": "autós",
    "ps": "ow-tos'",
    "df": "<b>αὖ</b> <font color='%COLOR_PURPLE%'>au</font> [tal vez afín a la base de <span style='color: #0000FF; cursor: pointer' class='Slink' onClick=strongFun('G109')>G109</span> con la idea de un viento desconcertante] (hacia atrás) pronombre reflexivo sí mismo, usado (solo o en el Compare <span style='color: #0000FF; cursor: pointer' class='Slink' onClick=strongFun('G1438')>G1438</span>) de la tercera persona, y (con el pronombre pers. apropiado) de las otras personas: <font color='%COLOR_BLUE%'>estas cosas, uno mismo, él, él mismo, ella mismo, este mismo, el mismo.</font> Compare <span style='color: #0000FF; cursor: pointer' class='Slink' onClick=strongFun('G848')>G848</span>."
  },
  {
    "id": "G847",
    "ti": "autoû",
    "le": "αὐτοῦ",
    "pl": "autú",
    "ps": "ow-too'",
    "df": "genitivo (i.e. posesivo) de <span style='color: #0000FF; cursor: pointer' class='Slink' onClick=strongFun('G846')>G846</span>, usado como un adverbio de lugar; propiamente perteneciente al mismo punto, i.e. en este (o este) lugar: <font color='%COLOR_BLUE%'>allí, aquí.</font>"
  },
  {
    "id": "G848",
    "ti": "hautoû",
    "le": "αὑτοῦ",
    "pl": "jautú",
    "ps": "how-too'",
    "df": "contracción de <span style='color: #0000FF; cursor: pointer' class='Slink' onClick=strongFun('G1438')>G1438</span>; -se, a sí mismo (en algún caso oblicuo o relación reflexivamente): <font color='%COLOR_BLUE%'>él mismo, ellos mismos, ellos.</font>"
  },
  {
    "id": "G849",
    "ti": "autócheir",
    "le": "αὐτόχειρ",
    "pl": "autójeir",
    "ps": "ow-tokh'-ire",
    "df": "de <span style='color: #0000FF; cursor: pointer' class='Slink' onClick=strongFun('G846')>G846</span> y <span style='color: #0000FF; cursor: pointer' class='Slink' onClick=strongFun('G5495')>G5495</span>; con sus propias manos, i.e. hacerlo personalmente: <font color='%COLOR_BLUE%'>con sus propias manos.</font>"
  },
  {
    "id": "G850",
    "ti": "auchmērós",
    "le": "αὐχμηρός",
    "pl": "aujmeros",
    "ps": "owkh-may-ros'",
    "df": "<b>αὐχμός</b> <font color='%COLOR_PURPLE%'>aujmós</font> [probablemente de una base afín a la de <span style='color: #0000FF; cursor: pointer' class='Slink' onClick=strongFun('G109')>G109</span>] (polvo, como secado por el viento) propiamente tierra, sucio, i.e. (por implicación) obscuro: <font color='%COLOR_BLUE%'>oscuro.</font>"
  },
  {
    "id": "G851",
    "ti": "aphairéō",
    "le": "ἀφαιρέω",
    "pl": "afairéo",
    "ps": "af-ahee-reh'-o",
    "df": "de <span style='color: #0000FF; cursor: pointer' class='Slink' onClick=strongFun('G575')>G575</span> y <span style='color: #0000FF; cursor: pointer' class='Slink' onClick=strongFun('G138')>G138</span>; remover (literalmente o figurativamente): <font color='%COLOR_BLUE%'>herir, cortar, quitar.</font>"
  },
  {
    "id": "G852",
    "ti": "aphanḗs",
    "le": "ἀφανής",
    "pl": "afanés",
    "ps": "af-an-ace'",
    "df": "de <span style='color: #0000FF; cursor: pointer' class='Slink' onClick=strongFun('G1')>G1</span> (como partícula negativa) y <span style='color: #0000FF; cursor: pointer' class='Slink' onClick=strongFun('G5316')>G5316</span>; no aparente): <font color='%COLOR_BLUE%'>no sea manifiesto.</font>"
  },
  {
    "id": "G853",
    "ti": "aphanízō",
    "le": "ἀφανίζω",
    "pl": "afanízo",
    "ps": "af-an-id'-zo",
    "df": "de <span style='color: #0000FF; cursor: pointer' class='Slink' onClick=strongFun('G852')>G852</span>; hacer no aparente, i.e. (activamente) consumir (nublar), o (pasivamente) desaparecer (ser destruido): <font color='%COLOR_BLUE%'>corromper, demudar, desaparecer, desvanecer.</font>"
  },
  {
    "id": "G854",
    "ti": "aphanismós",
    "le": "ἀφανισμός",
    "pl": "afanismós",
    "ps": "af-an-is-mos'",
    "df": "de <span style='color: #0000FF; cursor: pointer' class='Slink' onClick=strongFun('G853')>G853</span>; desaparición, i.e. (figurativamente) abrogación: <font color='%COLOR_BLUE%'>desaparecer.</font>"
  },
  {
    "id": "G855",
    "ti": "áphantos",
    "le": "ἄφαντος",
    "pl": "áfantos",
    "ps": "af'-an-tos",
    "df": "de <span style='color: #0000FF; cursor: pointer' class='Slink' onClick=strongFun('G1')>G1</span> (como partícula negativa) y un derivado de <span style='color: #0000FF; cursor: pointer' class='Slink' onClick=strongFun('G5316')>G5316</span>; no manifestado, i.e. invisible: <font color='%COLOR_BLUE%'>desaparecer.</font>"
  },
  {
    "id": "G856",
    "ti": "aphedrṓn",
    "le": "ἀφεδρών",
    "pl": "afedrón",
    "ps": "af-ed-rone'",
    "df": "de un compuesto de <span style='color: #0000FF; cursor: pointer' class='Slink' onClick=strongFun('G575')>G575</span> y la base de <span style='color: #0000FF; cursor: pointer' class='Slink' onClick=strongFun('G1476')>G1476</span>; un lugar de sentarse aparte, i.e. privado: <font color='%COLOR_BLUE%'>letrina.</font>"
  },
  {
    "id": "G857",
    "ti": "apheidía",
    "le": "ἀφειδία",
    "pl": "afeidía",
    "ps": "af-i-dee'-ah",
    "df": "de un compuesto de <span style='color: #0000FF; cursor: pointer' class='Slink' onClick=strongFun('G1')>G1</span> (como partícula negativa) y <span style='color: #0000FF; cursor: pointer' class='Slink' onClick=strongFun('G5339')>G5339</span>; sin liberalidad, i.e. austeridad (ascetismo): <font color='%COLOR_BLUE%'>duro trato.</font>"
  },
  {
    "id": "G858",
    "ti": "aphelótēs",
    "le": "ἀφελότης",
    "pl": "afelótes",
    "ps": "af-el-ot'-ace",
    "df": "de un compuesto de <span style='color: #0000FF; cursor: pointer' class='Slink' onClick=strongFun('G1')>G1</span> (como partícula negativa) y <b>φέλλος</b> <font color='%COLOR_PURPLE%'>félos</font> (en el sentido de piedra contra la que tropieza el pie); lisura, i.e. (figurativamente) simplicidad, sencillez: <font color='%COLOR_BLUE%'>sencillez.</font>"
  },
  {
    "id": "G859",
    "ti": "áphesis",
    "le": "ἄφεσις",
    "pl": "áfesis",
    "ps": "af'-es-is",
    "df": "de <span style='color: #0000FF; cursor: pointer' class='Slink' onClick=strongFun('G863')>G863</span>; libertad; (figurativamente) perdón: <font color='%COLOR_BLUE%'>perdón, remisión, libertad.</font>"
  },
  {
    "id": "G860",
    "ti": "haphḗ",
    "le": "ἁφή",
    "pl": "jafé",
    "ps": "haf-ay'",
    "df": "de <span style='color: #0000FF; cursor: pointer' class='Slink' onClick=strongFun('G680')>G680</span>; probablemente ligamento (como sujetando): <font color='%COLOR_BLUE%'>coyuntura, unir.</font>"
  },
  {
    "id": "G861",
    "ti": "aphtharsía",
    "le": "ἀφθαρσία",
    "pl": "afdsarsía",
    "ps": "af-thar-see'-ah",
    "df": "de <span style='color: #0000FF; cursor: pointer' class='Slink' onClick=strongFun('G862')>G862</span>; incorruptibilidad; generalmente existencia interminable; (figurativamente) autenticidad: <font color='%COLOR_BLUE%'>inalterable, incorrupción, inmortalidad.</font>"
  },
  {
    "id": "G862",
    "ti": "áphthartos",
    "le": "ἄφθαρτος",
    "pl": "áfdsartos",
    "ps": "af'-thar-tos",
    "df": "de <span style='color: #0000FF; cursor: pointer' class='Slink' onClick=strongFun('G1')>G1</span> (como partícula negativa) y un derivado de <span style='color: #0000FF; cursor: pointer' class='Slink' onClick=strongFun('G5351')>G5351</span>; sin decaer (en esencia o continuación): <font color='%COLOR_BLUE%'>incorruptible, inmortal,.</font>"
  },
  {
    "id": "G863",
    "ti": "aphíēmi",
    "le": "ἀφίημι",
    "pl": "afíemi",
    "ps": "af-ee'-ay-mee",
    "df": "de <span style='color: #0000FF; cursor: pointer' class='Slink' onClick=strongFun('G575')>G575</span> y <b>ἵημι</b> <font color='%COLOR_PURPLE%'>jíemi</font> (enviar; form. intensivo de <b>εἶμι</b> <font color='%COLOR_PURPLE%'>éimi</font>, ir); enviar, en varias aplicaciones (como sigue): <font color='%COLOR_BLUE%'>perdonar, permitir, quedar, salir, abandonar, consentir, dejar, despedir, entregar, remitir.</font>"
  },
  {
    "id": "G864",
    "ti": "aphiknéomai",
    "le": "ἀφικνέομαι",
    "pl": "afiknéomai",
    "ps": "af-ik-neh'-om-ahee",
    "df": "de <span style='color: #0000FF; cursor: pointer' class='Slink' onClick=strongFun('G575')>G575</span> y la base de <span style='color: #0000FF; cursor: pointer' class='Slink' onClick=strongFun('G2425')>G2425</span>; ir (i.e. esparcir, regar) (por rumor): <font color='%COLOR_BLUE%'>venir.</font>"
  },
  {
    "id": "G865",
    "ti": "aphilágathos",
    "le": "ἀφιλάγαθος",
    "pl": "afilágadsos",
    "ps": "af-il-ag'-ath-os",
    "df": "de <span style='color: #0000FF; cursor: pointer' class='Slink' onClick=strongFun('G1')>G1</span> (como partícula negativa) y <span style='color: #0000FF; cursor: pointer' class='Slink' onClick=strongFun('G5358')>G5358</span>; hostil a la virtud: <font color='%COLOR_BLUE%'>aborrecedor de lo bueno.</font>"
  },
  {
    "id": "G866",
    "ti": "aphilárgyros",
    "le": "ἀφιλάργυρος",
    "pl": "afilárguros",
    "ps": "af-il-ar'-goo-ros",
    "df": "de <span style='color: #0000FF; cursor: pointer' class='Slink' onClick=strongFun('G1')>G1</span> (como partícula negativa) y <span style='color: #0000FF; cursor: pointer' class='Slink' onClick=strongFun('G5366')>G5366</span>; sin avaricia: <font color='%COLOR_BLUE%'>sin avaricia, no avaro.</font>"
  },
  {
    "id": "G867",
    "ti": "áphixis",
    "le": "ἄφιξις",
    "pl": "áfixis",
    "ps": "af'-ix-is",
    "df": "de <span style='color: #0000FF; cursor: pointer' class='Slink' onClick=strongFun('G864')>G864</span>; propiamente arribo, llegada, i.e. (por implicación) partida: <font color='%COLOR_BLUE%'>partida.</font>"
  },
  {
    "id": "G868",
    "ti": "aphístēmi",
    "le": "ἀφίστημι",
    "pl": "afístemi",
    "ps": "af-is'-tay-mee",
    "df": "de <span style='color: #0000FF; cursor: pointer' class='Slink' onClick=strongFun('G575')>G575</span> y <span style='color: #0000FF; cursor: pointer' class='Slink' onClick=strongFun('G2476')>G2476</span>; remover, i.e. (activamente) instigar a la revuelta; por lo general (reflexivamente) desistir, desertar, etc.: <font color='%COLOR_BLUE%'>llevar, apartar, apostatar.</font>"
  },
  {
    "id": "G869",
    "ti": "áphnō",
    "le": "ἄφνω",
    "pl": "áfno",
    "ps": "af'-no",
    "df": "adverbio de <span style='color: #0000FF; cursor: pointer' class='Slink' onClick=strongFun('G852')>G852</span> (contracción); sin percatarse, i.e. inesperadamente: <font color='%COLOR_BLUE%'>de repente.</font>"
  },
  {
    "id": "G870",
    "ti": "aphóbōs",
    "le": "ἀφόβως",
    "pl": "afóbos",
    "ps": "af-ob'-oce",
    "df": "adverbio de un compuesto de <span style='color: #0000FF; cursor: pointer' class='Slink' onClick=strongFun('G1')>G1</span> (como partícula negativa) y <span style='color: #0000FF; cursor: pointer' class='Slink' onClick=strongFun('G5401')>G5401</span>; sin temor: <font color='%COLOR_BLUE%'>sin temor.</font>"
  },
  {
    "id": "G871",
    "ti": "aphomoióō",
    "le": "ἀφομοιόω",
    "pl": "afomoióo",
    "ps": "af-om-oy-o'-o",
    "df": "de <span style='color: #0000FF; cursor: pointer' class='Slink' onClick=strongFun('G575')>G575</span> y <span style='color: #0000FF; cursor: pointer' class='Slink' onClick=strongFun('G3666')>G3666</span>; asimilar estrechamente: <font color='%COLOR_BLUE%'>hecho semejante.</font>"
  },
  {
    "id": "G872",
    "ti": "aphoráō",
    "le": "ἀφοράω",
    "pl": "aforáo",
    "ps": "af-or-ah'-o",
    "df": "de <span style='color: #0000FF; cursor: pointer' class='Slink' onClick=strongFun('G575')>G575</span> y <span style='color: #0000FF; cursor: pointer' class='Slink' onClick=strongFun('G3708')>G3708</span>; considerar atentivamente: <font color='%COLOR_BLUE%'>poner los ojos.</font>"
  },
  {
    "id": "G873",
    "ti": "aphorízō",
    "le": "ἀφορίζω",
    "pl": "aforízo",
    "ps": "af-or-id'-zo",
    "df": "de <span style='color: #0000FF; cursor: pointer' class='Slink' onClick=strongFun('G575')>G575</span> y <span style='color: #0000FF; cursor: pointer' class='Slink' onClick=strongFun('G3724')>G3724</span>; dejar fuera por límite, i.e. (figurativamente) límite, excluir, nombrar, etc.: <font color='%COLOR_BLUE%'>separar, apartar.</font>"
  },
  {
    "id": "G874",
    "ti": "aphormḗ",
    "le": "ἀφορμή",
    "pl": "aformé",
    "ps": "af-or-may'",
    "df": "de un compuesto de <span style='color: #0000FF; cursor: pointer' class='Slink' onClick=strongFun('G575')>G575</span> y <span style='color: #0000FF; cursor: pointer' class='Slink' onClick=strongFun('G3729')>G3729</span>; punto de partida, i.e. (figurativamente) oportunidad: <font color='%COLOR_BLUE%'>ocasión.</font>"
  },
  {
    "id": "G875",
    "ti": "aphrízō",
    "le": "ἀφρίζω",
    "pl": "afrízo",
    "ps": "af-rid'-zo",
    "df": "de <span style='color: #0000FF; cursor: pointer' class='Slink' onClick=strongFun('G876')>G876</span>; echar espuma por la boca (en epilepsia): <font color='%COLOR_BLUE%'>espumarajo.</font>"
  },
  {
    "id": "G876",
    "ti": "aphrós",
    "le": "ἀφρός",
    "pl": "afrós",
    "ps": "af-ros'",
    "df": "aparentemente palabra primaria; echar espuma, i.e. babear: <font color='%COLOR_BLUE%'>espuma.</font>"
  },
  {
    "id": "G877",
    "ti": "aphrosýnē",
    "le": "ἀφροσύνη",
    "pl": "afrosúne",
    "ps": "af-ros-oo'-nay",
    "df": "de <span style='color: #0000FF; cursor: pointer' class='Slink' onClick=strongFun('G878')>G878</span>; sin sentido, i.e. (eufemismo) egotismo; (moralmente) insensatez: <font color='%COLOR_BLUE%'>insensatez, locura.</font>"
  },
  {
    "id": "G878",
    "ti": "áphrōn",
    "le": "ἄφρων",
    "pl": "áfron",
    "ps": "af'-rone",
    "df": "de <span style='color: #0000FF; cursor: pointer' class='Slink' onClick=strongFun('G1')>G1</span> (como partícula negativa) y <span style='color: #0000FF; cursor: pointer' class='Slink' onClick=strongFun('G5424')>G5424</span>; propiamente sin sentido, i.e. estúpido, (por implicación) ignorante, (específicamente) egotista, (prácticamente) imprudente, o (moralmente) incrédulo: <font color='%COLOR_BLUE%'>indocto, insensato, loco, necio.</font>"
  },
  {
    "id": "G879",
    "ti": "aphypnóō",
    "le": "ἀφυπνόω",
    "pl": "afupnóo",
    "ps": "af-oop-no'-o",
    "df": "de un compuesto de <span style='color: #0000FF; cursor: pointer' class='Slink' onClick=strongFun('G575')>G575</span> y <span style='color: #0000FF; cursor: pointer' class='Slink' onClick=strongFun('G5258')>G5258</span>; propiamente despertarse, i.e. (por implicación) caer en sueño: <font color='%COLOR_BLUE%'>dormirse.</font>"
  },
  {
    "id": "G880",
    "ti": "áphōnos",
    "le": "ἄφωνος",
    "pl": "áfonos",
    "ps": "af'-o-nos",
    "df": "de <span style='color: #0000FF; cursor: pointer' class='Slink' onClick=strongFun('G1')>G1</span> (como partícula negativa) y <span style='color: #0000FF; cursor: pointer' class='Slink' onClick=strongFun('G5456')>G5456</span>; sin voz, i.e. mudo (por naturaleza o decisión); figurativamente sin significa do: <font color='%COLOR_BLUE%'>muda, carece de significa do.</font>"
  },
  {
    "id": "G881",
    "ti": "Acház",
    "le": "Ἀχάζ",
    "pl": "Ajáz",
    "ps": "akh-adz'",
    "df": "de origen hebreo [<span style='color: #0000FF; cursor: pointer' class='Slink' onClick=strongFun('H271')>H271</span>]; Acaz, un israelita: <font color='%COLOR_BLUE%'>Acaz.</font>"
  },
  {
    "id": "G882",
    "ti": "Achaḯa",
    "le": "Ἀχαΐα",
    "pl": "Acjaía",
    "ps": "ach-ah-ee'-ah",
    "df": "de derivación incierta; Acaya (i.e. Grecia), una nación de Europa: <font color='%COLOR_BLUE%'>Acaya.</font>"
  },
  {
    "id": "G883",
    "ti": "Achaïkós",
    "le": "Ἀχαϊκός",
    "pl": "Ajaikós",
    "ps": "ach-ah-ee-kos'",
    "df": "de <span style='color: #0000FF; cursor: pointer' class='Slink' onClick=strongFun('G882')>G882</span>; aquéo; Acaico, un cristiano: <font color='%COLOR_BLUE%'>Acaico.</font>"
  },
  {
    "id": "G884",
    "ti": "acháristos",
    "le": "ἀχάριστος",
    "pl": "ajáristos",
    "ps": "ach-ar'-is-tos",
    "df": "de <span style='color: #0000FF; cursor: pointer' class='Slink' onClick=strongFun('G1')>G1</span> (como partícula negativa) y un derivado presunto de <span style='color: #0000FF; cursor: pointer' class='Slink' onClick=strongFun('G5483')>G5483</span>; desagradecido, i.e. ingrato: <font color='%COLOR_BLUE%'>ingrato.</font>"
  },
  {
    "id": "G885",
    "ti": "Acheím",
    "le": "Ἀχείμ",
    "pl": "Ajeím",
    "ps": "akh-ime'",
    "df": "o <b>Ἀχίμ</b> <font color='%COLOR_PURPLE%'>Ajím</font>; probablemente de origen hebreo [Compare <span style='color: #0000FF; cursor: pointer' class='Slink' onClick=strongFun('H3137')>H3137</span>]; Aquim, un israelita: <font color='%COLOR_BLUE%'>Aquim.</font>"
  },
  {
    "id": "G886",
    "ti": "acheiropoíētos",
    "le": "ἀχειροποίητος",
    "pl": "ajeiropoíetos",
    "ps": "akh-i-rop-oy'-ay-tos",
    "df": "de <span style='color: #0000FF; cursor: pointer' class='Slink' onClick=strongFun('G1')>G1</span> (como partícula negativa) y <span style='color: #0000FF; cursor: pointer' class='Slink' onClick=strongFun('G5499')>G5499</span>; no manufacturado, i.e. no artificial: <font color='%COLOR_BLUE%'>hecho sin mano.</font>"
  },
  {
    "id": "G887",
    "ti": "achlýs",
    "le": "ἀχλύς",
    "pl": "ajlús",
    "ps": "akh-looce'",
    "df": "de derivación incierta; nublado de vista, i.e. (probablemente) catarata: <font color='%COLOR_BLUE%'>oscuridad.</font>"
  },
  {
    "id": "G888",
    "ti": "achreîos",
    "le": "ἀχρεῖος",
    "pl": "ajréios",
    "ps": "akh-ri'-os",
    "df": "de <span style='color: #0000FF; cursor: pointer' class='Slink' onClick=strongFun('G1')>G1</span> (como partícula negativa) y un derivado de <span style='color: #0000FF; cursor: pointer' class='Slink' onClick=strongFun('G5534')>G5534</span> [Compare <span style='color: #0000FF; cursor: pointer' class='Slink' onClick=strongFun('G5532')>G5532</span>]; inútil, i.e. (eufemismo) no meritorio: <font color='%COLOR_BLUE%'>inútil.</font>"
  },
  {
    "id": "G889",
    "ti": "achreióō",
    "le": "ἀχρειόω",
    "pl": "ajreióo",
    "ps": "akh-ri-o'-o",
    "df": "de <span style='color: #0000FF; cursor: pointer' class='Slink' onClick=strongFun('G888')>G888</span>; hacer inútil, i.e. arruinar, estropear: <font color='%COLOR_BLUE%'>hacerse inútil.</font>"
  },
  {
    "id": "G890",
    "ti": "áchrēstos",
    "le": "ἄχρηστος",
    "pl": "ájrestos",
    "ps": "akh'-race-tos",
    "df": "de <span style='color: #0000FF; cursor: pointer' class='Slink' onClick=strongFun('G1')>G1</span> (como partícula negativa) y <span style='color: #0000FF; cursor: pointer' class='Slink' onClick=strongFun('G5543')>G5543</span>; ineficiente, i.e. (por implicación) perjudicial: <font color='%COLOR_BLUE%'>inútil.</font>"
  },
  {
    "id": "G891",
    "ti": "áchri",
    "le": "ἄχρι",
    "pl": "ájri",
    "ps": "akh'-ree",
    "df": "o <b>ἄχρις</b> <font color='%COLOR_PURPLE%'>ájris</font>; afín a <span style='color: #0000FF; cursor: pointer' class='Slink' onClick=strongFun('G206')>G206</span> (mediante la idea de un término); (de tiempo) hasta o (de lugar) hasta: <font color='%COLOR_BLUE%'>hasta.</font> Compare <span style='color: #0000FF; cursor: pointer' class='Slink' onClick=strongFun('G3360')>G3360</span>."
  },
  {
    "id": "G892",
    "ti": "áchyron",
    "le": "ἄχυρον",
    "pl": "ájuron",
    "ps": "akh'-oo-ron",
    "df": "tal vez remotamente de <b>χέω</b> <font color='%COLOR_PURPLE%'>jéo</font> (regar, esparcir); tamo (como que se esparce): <font color='%COLOR_BLUE%'>paja.</font>"
  },
  {
    "id": "G893",
    "ti": "apseudḗs",
    "le": "ἀψευδής",
    "pl": "apseudés",
    "ps": "aps-yoo-dace'",
    "df": "de <span style='color: #0000FF; cursor: pointer' class='Slink' onClick=strongFun('G1')>G1</span> (como partícula negativa) y <span style='color: #0000FF; cursor: pointer' class='Slink' onClick=strongFun('G5579')>G5579</span>; veraz: <font color='%COLOR_BLUE%'>que miente.</font>"
  },
  {
    "id": "G894",
    "ti": "ápsinthos",
    "le": "ἄψινθος",
    "pl": "ápsindsos",
    "ps": "ap'-sin-thos",
    "df": "de derivación incierta; polilla (como tipo de amargura, i.e. [figurativamente] calamidad): <font color='%COLOR_BLUE%'>ajenjo.</font>"
  },
  {
    "id": "G895",
    "ti": "ápsychos",
    "le": "ἄψυχος",
    "pl": "ápsujos",
    "ps": "ap'-soo-khos",
    "df": "de <span style='color: #0000FF; cursor: pointer' class='Slink' onClick=strongFun('G1')>G1</span> (como partícula negativa) y <span style='color: #0000FF; cursor: pointer' class='Slink' onClick=strongFun('G5590')>G5590</span>; sin vida, i.e. inanimado (mecánico): <font color='%COLOR_BLUE%'>inanimada.</font>"
  },
  {
    "id": "G896",
    "ti": "Báal",
    "le": "Βάαλ",
    "pl": "Báal",
    "ps": "bah'-al",
    "df": "de origen hebreo [<span style='color: #0000FF; cursor: pointer' class='Slink' onClick=strongFun('H1168')>H1168</span>]; Baal, deidad fenicia (usado como símbolo de idolatría): <font color='%COLOR_BLUE%'>Baal.</font>"
  },
  {
    "id": "G897",
    "ti": "Babylṓn",
    "le": "Βαβυλών",
    "pl": "Babulón",
    "ps": "bab-oo-lone'",
    "df": "de origen hebreo [<span style='color: #0000FF; cursor: pointer' class='Slink' onClick=strongFun('H894')>H894</span>]; Babilonia, capital de Caldea (literalmente o figurativamente [como tipo de tiranía]): <font color='%COLOR_BLUE%'>Babilonia.</font>"
  },
  {
    "id": "G898",
    "ti": "bathmós",
    "le": "βαθμός",
    "pl": "badsmós",
    "ps": "bath-mos'",
    "df": "de lo mismo que <span style='color: #0000FF; cursor: pointer' class='Slink' onClick=strongFun('G899')>G899</span>; paso, i.e. (figurativamente) grado (de dignidad): <font color='%COLOR_BLUE%'>grado.</font>"
  },
  {
    "id": "G899",
    "ti": "báthos",
    "le": "βάθος",
    "pl": "bádsos",
    "ps": "bath'-os",
    "df": "de lo mismo que <span style='color: #0000FF; cursor: pointer' class='Slink' onClick=strongFun('G901')>G901</span>; profundidad, i.e. (por implicación) extensión; (figurativamente) misterio: <font color='%COLOR_BLUE%'>profundidad, profundo.</font>"
  },
  {
    "id": "G900",
    "ti": "bathýnō",
    "le": "βαθύνω",
    "pl": "badsúno",
    "ps": "bath-oo'-no",
    "df": "de <span style='color: #0000FF; cursor: pointer' class='Slink' onClick=strongFun('G901')>G901</span>; profundizar: <font color='%COLOR_BLUE%'>ahondar.</font>"
  }
]
